porchlight/__init__.py
porchlight/door.py
porchlight/neighborhood.py
porchlight/param.py
porchlight/tests/README.md
porchlight/tests/__init__.py
porchlight/tests/test_basedoor.py
porchlight/tests/test_door.py
porchlight/tests/test_dynamicdoor.py
porchlight/tests/test_neighborhood.py
porchlight/tests/test_param.py
porchlight/tests/test_utils_inspect_functions.py
porchlight/tests/test_utils_typing_functions.py
porchlight/utils/__init__.py
porchlight/utils/inspect_functions.py
porchlight/utils/typing_functions.py
porchlight-1.1.0.dist-info/LICENSE
porchlight-1.1.0.dist-info/METADATA
porchlight-1.1.0.dist-info/WHEEL
porchlight-1.1.0.dist-info/RECORD
