Metadata-Version: 2.1
Name: porchlight
Version: 1.1.0
Summary: A function-managing package for models and systems with shared variables.
License: GPL-3.0-or-later
Author: Teal, D
Author-email: teal.dillon@gmail.com
Requires-Python: >=3.9,<4.0
Classifier: License :: OSI Approved :: GNU General Public License v3 or later (GPLv3+)
Classifier: Programming Language :: Python :: 3
Classifier: Programming Language :: Python :: 3.9
Classifier: Programming Language :: Python :: 3.10
Classifier: Programming Language :: Python :: 3.11
